CHANGES.txt
README.txt
setup.py
Products/__init__.py
Products.PloneTemplates.egg-info/PKG-INFO
Products.PloneTemplates.egg-info/SOURCES.txt
Products.PloneTemplates.egg-info/dependency_links.txt
Products.PloneTemplates.egg-info/namespace_packages.txt
Products.PloneTemplates.egg-info/not-zip-safe
Products.PloneTemplates.egg-info/requires.txt
Products.PloneTemplates.egg-info/top_level.txt
Products/PloneTemplates/PatchSchemas.py
Products/PloneTemplates/Permissions.py
Products/PloneTemplates/TemplateSchema.py
Products/PloneTemplates/TemplateTool.py
Products/PloneTemplates/__init__.py
Products/PloneTemplates/config.py
Products/PloneTemplates/configure.zcml
Products/PloneTemplates/tool.gif
Products/PloneTemplates/browser/__init__.py
Products/PloneTemplates/browser/configure.zcml
Products/PloneTemplates/browser/menu.py
Products/PloneTemplates/content/__init__.py
Products/PloneTemplates/content/template.py
Products/PloneTemplates/profiles/default/factorytool.xml
Products/PloneTemplates/profiles/default/metadata.xml
Products/PloneTemplates/profiles/default/propertiestool.xml
Products/PloneTemplates/profiles/default/skins.xml
Products/PloneTemplates/profiles/default/toolset.xml
Products/PloneTemplates/profiles/default/types.xml
Products/PloneTemplates/profiles/default/workflows.xml
Products/PloneTemplates/profiles/default/types/Template.xml
Products/PloneTemplates/skins/PloneTemplates/instantiateTemplate.cpy
Products/PloneTemplates/skins/PloneTemplates/instantiateTemplate.cpy.metadata
Products/PloneTemplates/skins/PloneTemplates/template_icon.png
Products/PloneTemplates/skins/PloneTemplates/template_icon.png.metadata
Products/PloneTemplates/skins/PloneTemplates/template_overview.pt
Products/PloneTemplates/skins/PloneTemplates/template_usage.cpt
Products/PloneTemplates/skins/PloneTemplates/template_usage.cpt.metadata
Products/PloneTemplates/skins/PloneTemplates/template_view.pt
Products/PloneTemplates/skins/PloneTemplates/template_view.pt.metadata
Products/PloneTemplates/tests/PloneTemplatesTestcase.py
Products/PloneTemplates/tests/__init__.py
Products/PloneTemplates/tests/testSetup.py
Products/PloneTemplates/tests/testTemplateCreation.py
Products/PloneTemplates/tests/testTemplateTool.py