Metadata-Version: 1.0
Name: Products.PloneTemplates
Version: 1.0.3
Summary: Content templates for Plone
Home-page: http://pypi.python.org/pypi/Products.PloneTemplates
Author: Danny Bloemendaal
Author-email: danny.bloemendaal@informaat.nl
License: ZPL
Keywords: Zope Plone Templates
Platform: UNKNOWN
Classifier: Programming Language :: Python
Classifier: Framework :: Zope2
Classifier: Framework :: Plone
